README.md
setup.py
./README.md
elseql/__init__.py
elseql/elseql.py
elseql/parser.py
elseql/search.py
elseql/version.py
elseql.egg-info/PKG-INFO
elseql.egg-info/SOURCES.txt
elseql.egg-info/dependency_links.txt
elseql.egg-info/entry_points.txt
elseql.egg-info/requires.txt
elseql.egg-info/top_level.txt