Metadata-Version: 1.1
Name: elseql
Version: 0.3.0
Summary: SQL-like command line client for ElasticSearch
Home-page: https://github.com/raff/elseql
Author: Raffaele Sena
Author-email: raff367@gmail.com
License: MIT
Platform: Posix; MacOS X; Windows
Classifier: Development Status :: 4 - Beta
Classifier: Environment :: Console
Classifier: Intended Audience :: Developers
Classifier: License :: OSI Approved :: MIT License
Classifier: Operating System :: OS Independent
Classifier: Topic :: Internet
Classifier: Topic :: Utilities
Classifier: Topic :: Database :: Front-Ends
Classifier: Topic :: Internet :: WWW/HTTP :: Indexing/Search
Classifier: Programming Language :: Python :: 2
Classifier: Programming Language :: Python :: 2.6
Classifier: Programming Language :: Python :: 2.7
